Metadata-Version: 1.0
Name: distributions-helper
Version: 1.0
Summary: Gaussian distributions
Home-page: UNKNOWN
Author: Samantha Sam-Inimgba
Author-email: s.sinimgba@gmail.com
License: UNKNOWN
Platform: UNKNOWN
